mkdocs_pdf/__init__.py
mkdocs_pdf/plugin.py
mkdocs_pdf-0.1.2.dist-info/LICENSE
mkdocs_pdf-0.1.2.dist-info/METADATA
mkdocs_pdf-0.1.2.dist-info/WHEEL
mkdocs_pdf-0.1.2.dist-info/entry_points.txt
mkdocs_pdf-0.1.2.dist-info/top_level.txt
mkdocs_pdf-0.1.2.dist-info/RECORD
