Metadata-Version: 2.1
Name: mkdocs-pdf
Version: 0.1.2
Summary: MkDocs plugin for embedding PDFs in a Markdown way
Author-email: Thomas Rooijakkers <thomas.rooijakkers@tno.nl>
Maintainer-email: Thomas Rooijakkers <thomas.rooijakkers@tno.nl>
License: MIT
Project-URL: Homepage, https://github.com/ThomasTNO/mkdocs-pdf
Project-URL: Source, https://github.com/ThomasTNO/mkdocs-pdf
Keywords: mkdocs,pdf,embed
Platform: any
Classifier: License :: OSI Approved :: MIT License
Classifier: Programming Language :: Python :: 3
Classifier: Operating System :: OS Independent
Classifier: Intended Audience :: Developers
Classifier: Intended Audience :: Information Technology
Requires-Python: >=3.7
License-File: LICENSE
Requires-Dist: lxml
